kmj_test_toolkit/__init__.py
kmj_test_toolkit/mqtt/__init__.py
kmj_test_toolkit/mqtt/_client.py
kmj_test_toolkit/stx_type/__init__.py
kmj_test_toolkit/stx_type/array_type.py
kmj_test_toolkit/stx_type/base_type.py
kmj_test_toolkit/stx_type/bit_type.py
kmj_test_toolkit/stx_type/boolean_type.py
kmj_test_toolkit/stx_type/exception.py
kmj_test_toolkit/stx_type/float_type.py
kmj_test_toolkit/stx_type/integer_type.py
kmj_test_toolkit/stx_type/string_type.py
kmj_test_toolkit/stx_type/structure_type.py
kmj_test_toolkit/util/__init__.py
kmj_test_toolkit/util/_logging.py
kmj_test_toolkit-0.0.6.dist-info/LICENSE
kmj_test_toolkit-0.0.6.dist-info/METADATA
kmj_test_toolkit-0.0.6.dist-info/WHEEL
kmj_test_toolkit-0.0.6.dist-info/top_level.txt
kmj_test_toolkit-0.0.6.dist-info/RECORD
