Metadata-Version: 2.1
Name: kmj-test-toolkit
Version: 0.0.6
Summary: kmj develop toolkit
Author-email: daegunsoftKmj <kmj@daegunsoft.com>
Project-URL: Homepage, https://github.com/daegunsoft-kmj/dgs-toolkit
Classifier: Programming Language :: Python :: 3
Classifier: License :: OSI Approved :: MIT License
Classifier: Operating System :: OS Independent
Requires-Python: >=3.9
License-File: LICENSE
Requires-Dist: paho-mqtt ==1.6.*
